deltaapply/__init__.py
deltaapply/cdc_operations.py
deltaapply/core.py
deltaapply/data_sources.py
deltaapply/exceptions.py
deltaapply/target_writers.py
deltaapply-0.0.2.dist-info/licenses/LICENSE
deltaapply-0.0.2.dist-info/METADATA
deltaapply-0.0.2.dist-info/WHEEL
deltaapply-0.0.2.dist-info/top_level.txt
deltaapply-0.0.2.dist-info/RECORD
