Metadata-Version: 2.4
Name: deltaapply
Version: 0.0.2
Summary: Change Data Capture und Anwendung von Inserts, Updates und Deletes
License: MIT
Requires-Python: >=3.12
License-File: LICENSE
Requires-Dist: pandas>=2.3.1
Requires-Dist: polars>=1.32.0
Requires-Dist: pyarrow>=21.0.0
Requires-Dist: sqlalchemy>=2.0.42
Dynamic: license-file
